deny_me/__init__.py
deny_me/exceptions.py
deny_me/password.py
deny_me/restrict.py
deny_me-1.1.dist-info/LICENSE
deny_me-1.1.dist-info/METADATA
deny_me-1.1.dist-info/WHEEL
deny_me-1.1.dist-info/top_level.txt
deny_me-1.1.dist-info/RECORD
